{
    "filename": "175C_187.jpg",
    "category": "ROYAL ACADEMY OF ARTS EUROPEAN MASTERS OF THE EIGHTEENTH CENTURY  1954: Campo Sant Angelo",
    "tags": [
        "ROYAL ACADEMY OF ARTS EUROPEAN MASTERS OF THE EIGHTEENTH CENTURY  1954: Campo Sant Angelo"
    ],
    "description": "ROYAL ACADEMY OF ARTS EUROPEAN MASTERS OF THE EIGHTEENTH CENTURY  1954: Campo Sant Angelo",
    "permalink": "https://dhlabsrv4.epfl.ch/iiif_replica/cini%2F175C%2F175C_187.jpg/full/full/0/default.jpg",
    "year": "1715",
    "x": "56.89525",
    "y": "53.07513"
}